toys/__init__.py
toys/excel.py
toys-0.2.0.dist-info/LICENSE
toys-0.2.0.dist-info/METADATA
toys-0.2.0.dist-info/WHEEL
toys-0.2.0.dist-info/top_level.txt
toys-0.2.0.dist-info/RECORD
